AUTHORS.rst
CONTRIBUTING.rst
LICENSE
MANIFEST.in
README.rst
requirements.txt
setup.cfg
setup.py
versioneer.py
borf/__init__.py
borf/__main__.py
borf/_version.py
borf/borf.py
borf/get_orfs.py
borf.egg-info/PKG-INFO
borf.egg-info/SOURCES.txt
borf.egg-info/dependency_links.txt
borf.egg-info/entry_points.txt
borf.egg-info/requires.txt
borf.egg-info/top_level.txt
borf/tests/__init__.py
borf/tests/test_borf.py
docs/Makefile
docs/make.bat
docs/source/conf.py
docs/source/index.rst
docs/source/installation.rst
docs/source/min_versions.rst
docs/source/release-history.rst
docs/source/usage.rst
test_data/test_frames.fa
test_data/test_getorfs.fa
test_data/test_mutliple_frame_orfs.fa
test_data/test_stopsitent.fa
test_data/test_trans_all_frames.fa