Metadata-Version: 2.1
Name: borf
Version: 1.2
Summary: ORF predictions from .fa files
Home-page: https://github.com/betsig/borf
Author: Beth Signal
Author-email: bethany.signal@uts.edu.au
License: MIT
Platform: UNKNOWN
Classifier: Development Status :: 2 - Pre-Alpha
Classifier: Natural Language :: English
Classifier: Programming Language :: Python :: 3
Requires-Python: >=3.5
